bt_ddos_shield/__init__.py
bt_ddos_shield/encryption.py
bt_ddos_shield/message.py
bt_ddos_shield/miner.py
bt_ddos_shield/s3_manager.py
bt_ddos_shield/utils.py
bt_ddos_shield/validator.py
bt_ddos_shield-0.1.0.dist-info/LICENSE
bt_ddos_shield-0.1.0.dist-info/METADATA
bt_ddos_shield-0.1.0.dist-info/WHEEL
bt_ddos_shield-0.1.0.dist-info/RECORD
