Metadata-Version: 2.1
Name: bt-ddos-shield
Version: 0.1.0
Summary: 
Requires-Python: >=3.12,<4.0
Classifier: Programming Language :: Python :: 3
Classifier: Programming Language :: Python :: 3.12
Requires-Dist: boto3 (>=1.35.27,<2.0.0)
Requires-Dist: eciespy (>=0.4.2,<0.5.0)
